odoo/addons/account_banking_mandate_contact/README.rst
odoo/addons/account_banking_mandate_contact/__init__.py
odoo/addons/account_banking_mandate_contact/__manifest__.py
odoo/addons/account_banking_mandate_contact/i18n/account_banking_mandate_contact.pot
odoo/addons/account_banking_mandate_contact/i18n/es.po
odoo/addons/account_banking_mandate_contact/i18n/it.po
odoo/addons/account_banking_mandate_contact/models/__init__.py
odoo/addons/account_banking_mandate_contact/models/account_move_line.py
odoo/addons/account_banking_mandate_contact/models/res_partner.py
odoo/addons/account_banking_mandate_contact/readme/CONTRIBUTORS.md
odoo/addons/account_banking_mandate_contact/readme/DESCRIPTION.md
odoo/addons/account_banking_mandate_contact/readme/USAGE.md
odoo/addons/account_banking_mandate_contact/static/description/icon.png
odoo/addons/account_banking_mandate_contact/static/description/index.html
odoo/addons/account_banking_mandate_contact/tests/__init__.py
odoo/addons/account_banking_mandate_contact/tests/test_account_payment_order.py
odoo/addons/account_banking_mandate_contact/views/res_partner.xml
odoo_addon_account_banking_mandate_contact-18.0.1.1.0.dist-info/METADATA
odoo_addon_account_banking_mandate_contact-18.0.1.1.0.dist-info/WHEEL
odoo_addon_account_banking_mandate_contact-18.0.1.1.0.dist-info/top_level.txt
odoo_addon_account_banking_mandate_contact-18.0.1.1.0.dist-info/RECORD
