Metadata-Version: 2.1
Name: odoo-addon-account_banking_mandate_contact
Version: 18.0.1.1.0
Requires-Python: >=3.10
Requires-Dist: odoo-addon-account_banking_mandate==18.0.*
Requires-Dist: odoo==18.0.*
Summary: Assign specific banking mandates in contact level
Home-page: https://github.com/OCA/bank-payment
License: AGPL-3
Author: Tecnativa, Odoo Community Association (OCA)
Author-email: support@odoo-community.org
Classifier: Programming Language :: Python
Classifier: Framework :: Odoo
Classifier: Framework :: Odoo :: 18.0
Classifier: License :: OSI Approved :: GNU Affero General Public License v3
Classifier: Development Status :: 5 - Production/Stable
